{
    "symbol": "MATIC",
    "address": "0x7D1AfA7B718fb893dB30A3aBc0Cfc608AaCfeBB0",
    "decimals": 18,
    "name": "Matic Token",
    "ens_address": "",
    "website": "",
    "logo": {
      "src": "",
      "width": "",
      "height": "",
      "ipfs_hash": ""
    },
    "support": {
      "email": "",
      "url": ""
    },
    "social": {
      "blog": "",
      "chat": "",
      "discord": "",
      "facebook": "",
      "forum": "",
      "github": "",
      "gitter": "",
      "instagram": "",
      "linkedin": "",
      "reddit": "",
      "slack": "",
      "telegram": "",
      "twitter": "",
      "youtube": ""
    }
}