{
  "symbol": "CTL",
  "address": "0xBf4cFD7d1eDeeEA5f6600827411B41A21eB08abd",
  "decimals": 2,
  "name": "CTL",
  "ens_address": "",
  "website": "",
  "logo": {
    "src": "",
    "width": "",
    "height": "",
    "ipfs_hash": ""
  },
  "support": {
    "email": "",
    "url": ""
  },
  "social": {
    "blog": "",
    "chat": "",
    "facebook": "",
    "forum": "",
    "github": "",
    "gitter": "",
    "instagram": "",
    "linkedin": "",
    "reddit": "",
    "slack": "",
    "telegram": "",
    "twitter": "",
    "youtube": ""
  }
}